MANIFEST.in
pyproject.toml
setup.cfg
TcdIce_slice/__init__.py
TcdIce_slice/camhost.ice
TcdIce_slice/device.ice
TcdIce_slice/encoder.ice
TcdIce_slice/focuser.ice
TcdIce_slice/meteo.ice
TcdIce_slice/mount.ice
TcdIce_slice/mover.ice
TcdIce_slice/selector.ice
TcdIce_slice/serv485x_ice.ice
TcdIce_slice/targetctl.ice
TcdIce_slice/tcd_ice_base.ice
TcdIce_slice/telescope.ice
custom_build_backend/backend.py
tcd_ice.egg-info/PKG-INFO
tcd_ice.egg-info/SOURCES.txt
tcd_ice.egg-info/dependency_links.txt
tcd_ice.egg-info/requires.txt
tcd_ice.egg-info/top_level.txt