Metadata-Version: 2.1
Name: tcd-ice
Version: 1.2.0
Summary: A distribution of ZeroC/ICE slice files for TCD project.
Author-email: Evgeny Klunko <eklunko@gmail.com>
Requires-Python: >=3.8
Requires-Dist: zeroc-ice
